setup.py
scrabbly/__init__.py
scrabbly/engine.py
scrabbly.egg-info/PKG-INFO
scrabbly.egg-info/SOURCES.txt
scrabbly.egg-info/dependency_links.txt
scrabbly.egg-info/top_level.txt