Metadata-Version: 1.0
Name: scrabbly
Version: 0.0.3
Summary: Scrabble engine
Home-page: UNKNOWN
Author: Juan Manuel García
Author-email: jmg.utn@gmail.com
License: GPL v3
Keywords: Scrabble
Platform: UNKNOWN
